{
  "key": "/subjects/travel",
  "name": "travel",
  "subject_type": "subject",
  "solr_query": "subject_key:\"travel\"",
  "work_count": 84262,
  "works": [
    {
      "key": "/works/OL53908W",
      "title": "Adventures of Huckleberry Finn",
      "edition_count": 2552,
      "cover_id": 8157718,
      "cover_edition_key": "OL7062714M",
      "subject": [
        "adventure and adventurers",
        "Adventure stories",
        "American fiction (fictional works by one author)",
        "American literature",
        "Boys",
        "Child and youth fiction",
        "Children's fiction",
        "child witnesses",
        "Courtship",
        "English language",
        "friendship",
        "Fugitive slaves",
        "history",
        "humor",
        "Humorous stories",
        "Juvenile fiction",
        "juvenile literature",
        "literature",
        "Loyalty",
        "Male friendship",
        "Manners and customs",
        "orphans",
        "Personnages",
        "Race relations",
        "rafting",
        "Rafting (Sports)",
        "Revenge",
        "Runaway children",
        "Runaways",
        "runaway teenagers",
        "satire",
        "Sisters",
        "slavery",
        "Slaves",
        "Social classes",
        "social history-United States-1800s",
        "Social life and customs",
        "Travel",
        "Voyage",
        "voyages and travels",
        "young men",
        "Young women",
        "American literature, history and criticism, 19th century",
        "American literature, outlines, syllabi, etc.",
        "American manuscripts",
        "amitie masculine",
        "Anglais (langue)",
        "boys in literature",
        "Dictionaries",
        "Dummies (Bookselling)",
        "enfants fugueurs",
        "English as a second language",
        "esclaves fugitifs",
        "Examinations",
        "Facsimiles",
        "Foreign speakers",
        "garcons",
        "Garçons",
        "Literary Criticism",
        "Long Now Manual for Civilization",
        "Manuscripts",
        "open_syllabus_project",
        "Readers",
        "Readers for new literates",
        "relations raciales",
        "Romans",
        "Rôle selon le sexe dans la littérature",
        "Specimens",
        "Study and teaching",
        "Study guides",
        "Fiction",
        "Huckleberry Finn (Fictitious character)",
        "Romans, nouvelles, etc. pour la jeunesse",
        "Voyages",
        "Amitié",
        "Histoire",
        "Fiction, general",
        "Mississippi river, fiction",
        "Missouri, fiction",
        "Adventure and adventurers, fiction",
        "Slavery, fiction",
        "Finn, huckleberry (fictitious character), fiction",
        "Runaways (Fictitious characters)",
        "Romans, nouvelles",
        "Friendship, fiction",
        "Boys, fiction",
        "Voyages and travels -- Fiction",
        "Friendship -- Fiction",
        "Slavery -- Fiction",
        "Mississippi River -- Fiction",
        "Missouri -- History -- 19th century -- Fiction",
        "Children's literature",
        "American fiction",
        "Roman américain",
        "Amitié masculine",
        "Livres en gros caractères",
        "Classes sociales",
        "Jeunes femmes",
        "Amours",
        "Sœurs",
        "Large print books",
        "Fictional Works Publication Type",
        "Adventures of Huckleberry Finn (Twain, Mark)",
        "Criticism and interpretation",
        "Race relations in literature",
        "Coming of age",
        "Huckleberry Finn (Fictional character)",
        "Humorous",
        "Action & Adventure",
        "Mississippi, fiction",
        "Enslaved persons, fiction",
        "Fiction, coming of age",
        "Fiction, humorous, general",
        "Southern states, fiction",
        "Finn, huckleberry",
        "Finn, huckleberry (fictitious character)",
        "Finn, huckleberry (fictitious character)--fiction",
        "Runaway children--fiction",
        "Male friendship--fiction",
        "Fugitive slaves--fiction",
        "Race relations--fiction",
        "Boys--fiction",
        "Ps1305 .a1 2003",
        "813/.4",
        "Twain, mark , 1835-1910",
        "Boys--travel",
        "Boys--travel--mississippi river--fiction",
        "Sex role in literature",
        "Boys--missouri--fiction",
        "Ps1305.a2 g73 1995",
        "Ps1305 .t93 1999",
        "Boys & men",
        "In literature",
        "Spanish",
        "French",
        "The adventures of huckleberry finn (twain)",
        "Relations raciales dans la littérature",
        "Huckleberry finn",
        "Finn, huckleberry (personnage fictif)",
        "Fiction, action & adventure",
        "Slaves, fiction",
        "Fiction, humorous",
        "United states, history",
        "Twain, mark, 1835-1910",
        "Sawyer, tom (fictitious character), fiction",
        "Literature and fiction, juvenile",
        "Fiction, historical",
        "Tom sawyer (fictitious character)",
        "Aventuras-",
        "Novelas-",
        "Libros infantiles",
        "Abenturak-",
        "Eleberriak-",
        "Haur eta gazteentzako liburuak",
        "Wit and humor",
        "History and criticism",
        "Library",
        "Personal copy",
        "Historical fiction",
        "African Americans",
        "Adventure fiction",
        "Large type books",
        "Missouri Hannibal",
        "Mississippi River"
      ],
      "ia_collection": [
        "additional_collections",
        "album_recordings",
        "americana",
        "americanuniversity-ol",
        "audio_bookspoetry",
        "audio_music",
        "bannedbooks",
        "barryuniversity-ol",
        "belmont-ol",
        "binghamton-ol",
        "bpljordan-ol",
        "brigham_young_university",
        "cdl",
        "cnusd-ol",
        "cornell",
        "cua-ol",
        "dartmouthlibrary-ol",
        "delawarecountydistrictlibrary",
        "delawarecountydistrictlibrary-ol",
        "denverpubliclibrary-ol",
        "drakeuniversity-ol",
        "duke_libraries",
        "europeanlibraries",
        "framingham-ol",
        "georgetown-university-law-library-ol",
        "getty",
        "greatbooks",
        "gutenberg",
        "gwulibraries-ol",
        "hamiltonpubliclibrary-ol",
        "iacl",
        "inlibrary",
        "internet-books",
        "internetarchivebooks",
        "ithacacollege-ol",
        "johnshopkins-ol",
        "kalamazoocollege-ol",
        "kellylibrary",
        "library_of_atlantis",
        "librivoxaudio",
        "marygrovecollege",
        "marymount-ol",
        "microfilm",
        "newyorkpubliclibrary",
        "occidentalcollegelibrary-ol",
        "openlibrary-d-ol",
        "popularchinesebooks",
        "printdisabled",
        "prscr",
        "randolph-macon-college-ol",
        "riceuniversity-ol",
        "robarts",
        "rochester-ol",
        "salisburyfreelibrary-ol",
        "standardebooks",
        "stmaryscountylibrary",
        "the-claremont-colleges-ol",
        "toronto",
        "trent_university",
        "tulsacc-ol",
        "uhmauicollege-ol",
        "unb-ol",
        "unclibraries",
        "uni-ol",
        "university_of_alberta_libraries",
        "university_of_alberta_libraries_microfilm",
        "university_of_illinois_urbana-champaign",
        "university_of_toronto",
        "universityofarizona-ol",
        "universityofcoloradoboulder-ol",
        "universityofoklahoma-ol",
        "universityofthewest-ol",
        "unlockedrecordings",
        "urbanschool",
        "vinyl_bostonpubliclibrary",
        "wilsoncollege-ol",
        "worksintranslation",
        "worthingtonlibraries-ol",
        "wrlc-ol",
        "yrlsc"
      ],
      "printdisabled": true,
      "lending_edition": "OL48061167M",
      "lending_identifier": "adventuresofhuck0000mark_f4w4",
      "authors": [
        {
          "key": "/authors/OL18319A",
          "name": "Mark Twain"
        }
      ],
      "first_publish_year": 1876,
      "ia": "adventuresofhuck0000mark_f4w4",
      "public_scan": true,
      "has_fulltext": true,
      "availability": {
        "status": "open",
        "available_to_browse": false,
        "available_to_borrow": false,
        "available_to_waitlist": false,
        "is_printdisabled": false,
        "is_readable": true,
        "is_lendable": false,
        "is_previewable": true,
        "identifier": "adventuresofhuck0000mark_f4w4",
        "isbn": null,
        "oclc": null,
        "openlibrary_work": "OL53908W",
        "openlibrary_edition": "OL48061167M",
        "last_loan_date": null,
        "num_waitlist": null,
        "last_waitlist_date": null,
        "is_restricted": false,
        "is_browseable": false,
        "__src__": "core.models.lending.get_availability"
      }
    },
    {
      "key": "/works/OL450063W",
      "title": "Frankenstein or The Modern Prometheus",
      "edition_count": 2186,
      "cover_id": 12356249,
      "cover_edition_key": "OL35649409M",
      "subject": [
        "Frankenstein (Fictitious character)",
        "Frankenstein's monster (Fictitious character)",
        "Fiction",
        "Victor Frankenstein (Fictitious character)",
        "Scientists",
        "Monsters",
        "Fiction, horror",
        "Frankenstein (fictitious character), fiction",
        "Physicians, fiction",
        "British fiction (fictional works by one author)",
        "Scientists, fiction",
        "Geneva (Switzerland), fiction",
        "Children's fiction",
        "Horror stories",
        "Fiction, science fiction, general",
        "Fiction, general",
        "Horror tales",
        "Frankenstein (Shelley, Mary Wollstonecraft)",
        "Large type books",
        "English fiction",
        "Study guides",
        "Examinations",
        "Criticism and interpretation",
        "Fiction, gothic",
        "English language, textbooks for foreign speakers",
        "Reading comprehension",
        "Monsters, fiction",
        "English literature",
        "Comics & graphic novels, science fiction",
        "Comics & graphic novels, horror",
        "Comic books, strips, etc.",
        "Comics & graphic novels, literary",
        "Shelley, Mary Wollstonecraft, 1797-1851",
        "English fiction (collections), 19th century",
        "Literature and fiction, horror and ghost stories",
        "Readers",
        "Science fiction, history and criticism",
        "Horror tales, history and criticism",
        "Children's stories",
        "Monstrous",
        "Novela",
        "History and criticism",
        "Horror fiction",
        "British and irish fiction (fictional works by one author)",
        "Fiction, historical, general",
        "literary criticism",
        "English Science fiction",
        "English Horror tales",
        "Scientists in literature",
        "Monsters in literature",
        "Science, experiments, fiction",
        "Authors",
        "Travel",
        "Reincarnation",
        "Self-actualization (Psychology)",
        "Vida espiritual",
        "Arte de vivir",
        "Conducta (Ética)",
        "Self-realization",
        "Reading materials",
        "Fiction, science fiction, hard science fiction",
        "Switzerland, fiction",
        "Literature and fiction, women authors",
        "Literature, history and criticism",
        "Science fiction",
        "Cartoons and comics",
        "Monstres",
        "Romans, nouvelles",
        "Comic books, strips",
        "Classic science fiction",
        "Horror and supernatural fiction",
        "Classic fiction",
        "Science in literature",
        "Illustration",
        "Gothic fiction",
        "English language, juvenile literature",
        "Shelley, Mary Wollstonecraft, 1797-1851. Frankenstein",
        "Frankenstein, Victor (Fictitious character) -- Fiction",
        "Frankenstein's monster (Fictitious character) -- Fiction",
        "Scientists -- Fiction",
        "Monsters -- Fiction",
        "Frankenstein’s monster (Fictitious character)",
        "Frankenstein’s monster",
        "Monsters--fiction",
        "Frankenstein, victor (fictitious character)",
        "Frankenstein, victor (fictitious character)--fiction",
        "Pr5397 .f7 1992",
        "823.7 f",
        "Frankenstein, victor",
        "Frankenstein's monster",
        "Scientists--fiction",
        "Frankenstein, victor (fictional character)",
        "Frankenstein, victor (fictional character)--fiction",
        "Frankenstein (fictional character)",
        "Frankenstein (fictional character)--fiction",
        "Pr5397 .f7 2003c",
        "823/.7",
        "Fic004000",
        "Pr5397 .f7 1969",
        "Pr5397 .f7 2008f",
        "823.7",
        "Science & technology in literature",
        "Literary styles & movements - fiction",
        "Books at the movies",
        "Occupations - fiction",
        "English fiction & prose literature - general & miscellaneous - literary criticism",
        "Horror literature - literary criticism",
        "English",
        "Scot",
        "Pr5397 .f7 2007",
        "Shelley, mary wollstonecraft , 1797-1851",
        "Pr5397 .f7 2012",
        "Classics",
        "Horror",
        "Gothic",
        "English & college success -> english -> fiction",
        "Mary shelley",
        "Mary wollstonecraft shelley",
        "Women authors",
        "Rhetoric",
        "Ya",
        "Young adult",
        "Juvenile",
        "History",
        "Historical",
        "Classic",
        "Literature",
        "Books",
        "Novels",
        "Hardcovers",
        "Paperback",
        "Ebook",
        "Audio-book",
        "Stories",
        "Tales",
        "Madness",
        "Mad",
        "Science",
        "Life conduct",
        "Ethics",
        "Translations into russian",
        "Ficción",
        "Frankenstein (personaje literario)",
        "Monstruos",
        "Epistolary fiction",
        "Conducta (etica)",
        "ghost",
        "Frankenstein films",
        "Juvenile fiction",
        "African american women",
        "Man-woman relationships",
        "Pr5397 .f7 2012d",
        "Pr5397 .f7 2008d",
        "823",
        "Drama (dramatic works by one author)",
        "Long Now Manual for Civilization",
        "Victor Frankenstein (Fictional character)",
        "Criticism & interpretation"
      ],
      "ia_collection": [
        "additional_collections",
        "americana",
        "americanuniversity-ol",
        "barryuniversity-ol",
        "binghamton-ol",
        "bpljordan-ol",
        "cnusd-ol",
        "cornell",
        "dartmouthlibrary-ol",
        "delawarecountydistrictlibrary",
        "delawarecountydistrictlibrary-ol",
        "fedlink",
        "framingham-ol",
        "gwulibraries-ol",
        "hamiltonpubliclibrary-ol",
        "inlibrary",
        "internetarchivebooks",
        "johnshopkins-ol",
        "library_of_atlantis",
        "library_of_congress",
        "marygrovecollege",
        "marymount-ol",
        "miltonpubliclibrary-ol",
        "occidentalcollegelibrary-ol",
        "openlibrary-d-ol",
        "printdisabled",
        "riceuniversity-ol",
        "robarts",
        "rochester-ol",
        "sciencefiction",
        "stmaryscountylibrary",
        "the-claremont-colleges-ol",
        "toronto",
        "trent_university",
        "tulsacc-ol",
        "udc-ol",
        "unb-ol",
        "uni-ol",
        "university_of_toronto",
        "universityofarizona-ol",
        "universityofcoloradoboulder-ol",
        "universityofoklahoma-ol",
        "universityofthewest-ol",
        "wilsoncollege-ol",
        "worthingtonlibraries-ol"
      ],
      "printdisabled": true,
      "lending_edition": "OL26683337M",
      "lending_identifier": "frankensteinormo00shel_8",
      "authors": [
        {
          "key": "/authors/OL25342A",
          "name": "Mary Shelley"
        }
      ],
      "first_publish_year": 1818,
      "ia": "frankensteinormo00shel_8",
      "public_scan": true,
      "has_fulltext": true,
      "availability": {
        "status": "open",
        "available_to_browse": false,
        "available_to_borrow": false,
        "available_to_waitlist": false,
        "is_printdisabled": false,
        "is_readable": true,
        "is_lendable": false,
        "is_previewable": true,
        "identifier": "frankensteinormo00shel_8",
        "isbn": null,
        "oclc": null,
        "openlibrary_work": "OL18300402W",
        "openlibrary_edition": "OL26683337M",
        "last_loan_date": null,
        "num_waitlist": null,
        "last_waitlist_date": null,
        "is_restricted": false,
        "is_browseable": false,
        "__src__": "core.models.lending.get_availability"
      }
    },
    {
      "key": "/works/OL1793164W",
      "title": "Three Men in a Boat (to say nothing of the dog)",
      "edition_count": 1133,
      "cover_id": 8243006,
      "cover_edition_key": "OL23348263M",
      "subject": [
        "Humorous stories",
        "Male friendship",
        "Description and travel",
        "Humor (Fiction)",
        "Boats and boating",
        "Fiction",
        "Classic Literature",
        "English Humorous stories",
        "History",
        "General",
        "Fiction, humorous",
        "England, fiction",
        "Germany, fiction",
        "British and irish fiction (fictional works by one author)",
        "Friendship, fiction",
        "Children's fiction",
        "Boats and boating, fiction",
        "Dogs, fiction",
        "Travel",
        "Dogs",
        "Young men",
        "Large type books",
        "Humorous",
        "Classics",
        "Friendship",
        "Humorous fiction",
        "Freundeskreis",
        "Wasserwandern",
        "Fiction, humorous, general",
        "Male friendship in fiction",
        "Boats and boating in fiction",
        "Boats and boating x Fiction",
        "Wit and humor",
        "Fiction, historical, general",
        "English language, textbooks for foreign speakers",
        "Comics & graphic novels, general",
        "English literature",
        "Fiction, general",
        "Drama",
        "Adventure stories",
        "American wit and humor",
        "Readers (Adult)",
        "English language",
        "Textbooks for foreign speakers",
        "Reading comprehension",
        "Problems, exercises",
        "British",
        "English fiction",
        "Jeunes hommes",
        "Romans, nouvelles",
        "Long Now Manual for Civilization",
        "Bootsfahrt",
        "Englisch",
        "Roman",
        "Belletristische Darstellung",
        "Spanish language materials",
        "Text-books for foreigners",
        "Readers",
        "Thames River (England)",
        "Study and teaching",
        "Sale Books"
      ],
      "ia_collection": [
        "americana",
        "binghamton-ol",
        "cdl",
        "delawarecountydistrictlibrary",
        "hamiltonpubliclibrary-ol",
        "inlibrary",
        "internetarchivebooks",
        "johnshopkins-ol",
        "library_of_atlantis",
        "openlibrary-d-ol",
        "printdisabled",
        "rochester-ol",
        "tesseract_test",
        "toronto",
        "university_of_illinois_urbana-champaign"
      ],
      "printdisabled": true,
      "lending_edition": "OL59078019M",
      "lending_identifier": "threemeninboat0000jero_m3e9",
      "authors": [
        {
          "key": "/authors/OL215610A",
          "name": "Jerome Klapka Jérôme"
        }
      ],
      "first_publish_year": 1889,
      "ia": "threemeninboat0000jero_m3e9",
      "public_scan": true,
      "has_fulltext": true,
      "availability": {
        "status": "open",
        "available_to_browse": false,
        "available_to_borrow": false,
        "available_to_waitlist": false,
        "is_printdisabled": false,
        "is_readable": true,
        "is_lendable": false,
        "is_previewable": true,
        "identifier": "threemeninboat0000jero_m3e9",
        "isbn": null,
        "oclc": null,
        "openlibrary_work": "OL43375592W",
        "openlibrary_edition": "OL59078019M",
        "last_loan_date": null,
        "num_waitlist": null,
        "last_waitlist_date": null,
        "is_restricted": false,
        "is_browseable": false,
        "__src__": "core.models.lending.get_availability"
      }
    },
    {
      "key": "/works/OL17448W",
      "title": "King Solomon's Mines",
      "edition_count": 970,
      "cover_id": 8665393,
      "cover_edition_key": "OL27047031M",
      "subject": [
        "Children's fiction",
        "Mines and mineral resources, fiction",
        "Adventure and adventurers, fiction",
        "Large type books",
        "Quatermain, allan (fictitious character), fiction",
        "Fiction, action & adventure",
        "Africa -- Fiction",
        "Missing persons -- Fiction",
        "Adventure stories",
        "Treasure troves -- Fiction",
        "Hunting guides -- Fiction",
        "Diamond mines and mining -- Fiction",
        "Quatermain, Allan (Fictitious character) -- Fiction",
        "Fiction",
        "Allan Quatermain (Fictitious character)",
        "Treasure troves",
        "Diamond mines and mining",
        "Hunting guides",
        "Missing persons",
        "Adventure and adventurers",
        "Ficción",
        "Quatermain, Allan (Personaje literario)",
        "Buried treasure",
        "English language",
        "Text-books for foreigners",
        "Personas desaparecidas",
        "Tesoros ocultos",
        "Guías de caza",
        "Translations into Portuguese",
        "English Adventure stories",
        "Literature",
        "Classic Literature",
        "Roman anglais",
        "South africa, fiction",
        "Missing persons, fiction",
        "Africa, fiction",
        "Young adult fiction",
        "Adventure fiction",
        "Lost World",
        "British and irish fiction (fictional works by one author)",
        "Quatermain, Allan (Personnages fictifs)",
        "Romans, nouvelles",
        "Treasure-troves",
        "Juvenile fiction",
        "English literature",
        "Fiction, thrillers, general",
        "Reference foreign languages instruction english as a f aaaa0",
        "Reference foreign languages instruction english as a foreign",
        "Reference foreign languages general",
        "Long Now Manual for Civilization",
        "Spanish language books",
        "Readers",
        "Spanish language",
        "Solomon, king of israel, fiction",
        "Fiction, fantasy, general",
        "English language, textbooks for foreign speakers",
        "Swahili language",
        "Texts",
        "Solomon, king of israel",
        "Fiction, historical, general",
        "Description and travel",
        "Travel"
      ],
      "ia_collection": [
        "americana",
        "gwulibraries-ol",
        "hamiltonpubliclibrary-ol",
        "inlibrary",
        "internetarchivebooks",
        "library_of_congress",
        "openlibrary-d-ol",
        "popularchinesebooks",
        "printdisabled",
        "robarts",
        "toronto",
        "university_of_toronto",
        "universityofarizona-ol",
        "universityofcoloradoboulder-ol",
        "wrlc-ol"
      ],
      "printdisabled": true,
      "lending_edition": "OL58898811M",
      "lending_identifier": "kingsolomonsmnes0000hrid",
      "authors": [
        {
          "key": "/authors/OL23326A",
          "name": "H. Rider Haggard"
        }
      ],
      "first_publish_year": 1880,
      "ia": "kingsolomonsmnes0000hrid",
      "public_scan": true,
      "has_fulltext": true,
      "availability": {
        "status": "open",
        "available_to_browse": false,
        "available_to_borrow": false,
        "available_to_waitlist": false,
        "is_printdisabled": false,
        "is_readable": true,
        "is_lendable": false,
        "is_previewable": true,
        "identifier": "kingsolomonsmnes0000hrid",
        "isbn": null,
        "oclc": null,
        "openlibrary_work": "OL43245016W",
        "openlibrary_edition": "OL58898811M",
        "last_loan_date": null,
        "num_waitlist": null,
        "last_waitlist_date": null,
        "is_restricted": false,
        "is_browseable": false,
        "__src__": "core.models.lending.get_availability"
      }
    },
    {
      "key": "/works/OL54031W",
      "title": "A Connecticut Yankee in King Arthur's Court",
      "edition_count": 788,
      "cover_id": 9168732,
      "cover_edition_key": "OL6338772M",
      "subject": [
        "Time travel",
        "Fiction",
        "Arthurian romances",
        "Kings and rulers",
        "Adaptations",
        "Knights and knighthood",
        "Americans",
        "Britons",
        "American fiction (fictional works by one author)",
        "Fiction, fantasy, historical",
        "Great britain, fiction",
        "Arthur, king, fiction",
        "Camelot (legendary place), fiction",
        "England, fiction",
        "Fiction, humorous",
        "Fiction, satire",
        "Middle Ages",
        "Medievalism",
        "Middle Ages in literature",
        "History",
        "Juvenile fiction",
        "Large type books",
        "Travel",
        "King Arthur",
        "Connecticut Yankee in King Arthur's court (Twain, Mark)",
        "Life on the Mississippi (Twain, Mark)",
        "Mysterious stranger and other stories (Twain, Mark)",
        "Children's fiction",
        "Knights and knighthood, fiction",
        "Literature and fiction, historical fiction",
        "Literature and fiction, fantasy",
        "Fiction, fantasy, general",
        "History and criticism",
        "Arthurian romances, adaptations",
        "Criticism and interpretation",
        "Fiction, action & adventure",
        "Fantasy fiction",
        "Satire",
        "Knights and knighthood -- Fiction",
        "Arthurian romances -- Adaptations",
        "Time travel -- Fiction",
        "Americans -- Great Britain -- Fiction",
        "Kings and rulers -- Fiction",
        "Britons -- Fiction",
        "Twain, mark, 1835-1910",
        "Dictionaries",
        "English language",
        "German",
        "Moyen Âge",
        "Romans, nouvelles",
        "Voyages dans le temps",
        "Long Now Manual for Civilization",
        "literature",
        "18.06 Anglo-American literature"
      ],
      "ia_collection": [
        "additional_collections",
        "americana",
        "americanuniversity-ol",
        "audio_bookspoetry",
        "belmont-ol",
        "binghamton-ol",
        "brigham_young_university",
        "cdl",
        "cnusd-ol",
        "cornell",
        "dartmouthlibrary-ol",
        "delawarecountydistrictlibrary-ol",
        "drakeuniversity-ol",
        "europeanlibraries",
        "framingham-ol",
        "gutenberg",
        "gwulibraries-ol",
        "hamiltonpubliclibrary-ol",
        "inlibrary",
        "internetarchivebooks",
        "johnshopkins-ol",
        "kalamazoocollege-ol",
        "librivoxaudio",
        "marygrovecollege",
        "marymount-ol",
        "microfilm",
        "newyorkpubliclibrary",
        "occidentalcollegelibrary-ol",
        "openlibrary-d-ol",
        "printdisabled",
        "randolph-macon-college-ol",
        "riceuniversity-ol",
        "robarts",
        "rochester-ol",
        "sciencefiction",
        "standardebooks",
        "stmaryscountylibrary",
        "the-claremont-colleges-ol",
        "thomasfisher",
        "thomasfishercanadiana",
        "toronto",
        "uni-ol",
        "universallibrary",
        "university_of_alberta_libraries",
        "university_of_alberta_libraries_microfilm",
        "university_of_toronto",
        "universityofarizona-ol",
        "universityofcoloradoboulder-ol",
        "universityofoklahoma-ol",
        "wilsoncollege-ol",
        "worthingtonlibraries-ol"
      ],
      "printdisabled": true,
      "lending_edition": "OL45781517M",
      "lending_identifier": "connecticutyanke0000mark_r8h8",
      "authors": [
        {
          "key": "/authors/OL18319A",
          "name": "Mark Twain"
        }
      ],
      "first_publish_year": 1889,
      "ia": "connecticutyanke0000mark_r8h8",
      "public_scan": true,
      "has_fulltext": true,
      "availability": {
        "status": "open",
        "available_to_browse": false,
        "available_to_borrow": false,
        "available_to_waitlist": false,
        "is_printdisabled": false,
        "is_readable": true,
        "is_lendable": false,
        "is_previewable": true,
        "identifier": "connecticutyanke0000mark_r8h8",
        "isbn": null,
        "oclc": null,
        "openlibrary_work": "OL54031W",
        "openlibrary_edition": "OL45781517M",
        "last_loan_date": null,
        "num_waitlist": null,
        "last_waitlist_date": null,
        "is_restricted": false,
        "is_browseable": false,
        "__src__": "core.models.lending.get_availability"
      }
    },
    {
      "key": "/works/OL245401W",
      "title": "The Prisoner of Zenda",
      "edition_count": 625,
      "cover_id": 105814,
      "cover_edition_key": "OL7357137M",
      "subject": [
        "Fiction",
        "Adventure",
        "Fiction, action & adventure",
        "Ruritania (imaginary place), fiction",
        "British and irish fiction (fictional works by one author)",
        "Children's fiction",
        "Adventure and adventurers, fiction",
        "British",
        "Impostors and imposture",
        "English Adventure stories",
        "Classic Literature",
        "Foreign countries",
        "Thriller",
        "Literature",
        "Upper class",
        "Attempted murder",
        "Treason",
        "Travel",
        "Adventure stories",
        "Great britain, fiction",
        "Europe, fiction",
        "ELT graded readers",
        "English language readers",
        "Children's All Ages - Fiction - Adventure",
        "Revenge in fiction",
        "English literature",
        "Readers",
        "Fiction, general",
        "Kings and rulers",
        "Political kidnapping",
        "Classics",
        "Impostors and imposture -- Fiction",
        "British -- Foreign countries -- Fiction",
        "Fiction, historical, general",
        "Collectors and collecting",
        "Impersonation",
        "Large type books",
        "Prisoners",
        "Anglais (Langue)",
        "Lectures et morceaux choisis",
        "Prisonniers",
        "Romans, nouvelles",
        "English language, textbooks for foreign speakers",
        "Crime, fiction",
        "Kings, queens, rulers, etc., fiction",
        "English language",
        "Readers (Adult)",
        "Study and teaching",
        "Foreign speakers",
        "Étude et enseignement",
        "Allophones",
        "Long now manual for civilization"
      ],
      "ia_collection": [
        "additional_collections",
        "americana",
        "belmont-ol",
        "bostonpubliclibrary",
        "bpljordanresearch",
        "brigham_young_university",
        "cdl",
        "inlibrary",
        "internetarchivebooks",
        "library_of_congress",
        "marygrovecollege",
        "microfilm",
        "miltonpubliclibrary-ol",
        "popularchinesebooks",
        "printdisabled",
        "rochester-ol",
        "thomasfisher",
        "thomasfishercanadiana",
        "toronto",
        "trent_university",
        "ualberta_historical_school",
        "ualbertawiedrick",
        "university_of_alberta_libraries",
        "university_of_alberta_libraries_microfilm",
        "university_of_toronto",
        "universityofcoloradoboulder-ol",
        "worthingtonlibraries-ol"
      ],
      "printdisabled": true,
      "lending_edition": "OL26526103M",
      "lending_identifier": "prisonerofzendab00hope_3",
      "authors": [
        {
          "key": "/authors/OL27107A",
          "name": "Anthony Hope"
        },
        {
          "key": "/authors/OL577481A",
          "name": "Gary Hoppenstand"
        },
        {
          "key": "/authors/OL2662747A",
          "name": "Diane Mowat"
        },
        {
          "key": "/authors/OL578236A",
          "name": "Alan Marks"
        },
        {
          "key": "/authors/OL7995575A",
          "name": "Francesc Ràfols"
        },
        {
          "key": "/authors/OL9303114A",
          "name": "Andrew Pugsley"
        },
        {
          "key": "/authors/OL9788479A",
          "name": "Summer M. Hogan"
        },
        {
          "key": "/authors/OL10079370A",
          "name": "Summer Hogan"
        },
        {
          "key": "/authors/OL9615191A",
          "name": "Smidgen Press"
        },
        {
          "key": "/authors/OL6020283A",
          "name": "Charles Dana Gibson"
        },
        {
          "key": "/authors/OL11106329A",
          "name": "Daniel Lanza Barba"
        },
        {
          "key": "/authors/OL11106330A",
          "name": "Javier Fornell Fernandez"
        },
        {
          "key": "/authors/OL2956052A",
          "name": "Stephen Colbourn"
        },
        {
          "key": "/authors/OL7307550A",
          "name": "Katy Jackson"
        },
        {
          "key": "/authors/OL9109391A",
          "name": "James Wilby"
        },
        {
          "key": "/authors/OL674610A",
          "name": "Robinson, M."
        }
      ],
      "first_publish_year": 1800,
      "ia": "prisonerofzendab00hope_3",
      "public_scan": true,
      "has_fulltext": true,
      "availability": {
        "status": "open",
        "available_to_browse": false,
        "available_to_borrow": false,
        "available_to_waitlist": false,
        "is_printdisabled": false,
        "is_readable": true,
        "is_lendable": false,
        "is_previewable": true,
        "identifier": "prisonerofzendab00hope_3",
        "isbn": null,
        "oclc": null,
        "openlibrary_work": "OL17937845W",
        "openlibrary_edition": "OL26526103M",
        "last_loan_date": null,
        "num_waitlist": null,
        "last_waitlist_date": null,
        "is_restricted": false,
        "is_browseable": false,
        "__src__": "core.models.lending.get_availability"
      }
    },
    {
      "key": "/works/OL38663W",
      "title": "Heart of Darkness",
      "edition_count": 552,
      "cover_id": 12307847,
      "cover_edition_key": "OL35601698M",
      "subject": [
        "Fiction",
        "Romance",
        "Degeneration",
        "Literature",
        "Description and travel",
        "Diaries",
        "Sailors",
        "Short stories",
        "English literature",
        "Suffering",
        "Trading posts",
        "Classic Literature",
        "Travel",
        "Discovery and exploration",
        "Mystery",
        "Open Library Staff Picks",
        "Drama",
        "Fugitives from justice",
        "English Psychological fiction",
        "LITERATURA INGLESA (HISTÓRIA E CRÍTICA)",
        "Ship captains",
        "Conrad, Joseph, 1857-1924. Heart of darkness",
        "Heart of darkness (Conrad)",
        "Journeys",
        "History and criticism",
        "Imperialism",
        "Europeans",
        "Long Now Manual for Civilization",
        "Romans",
        "Souffrance",
        "Literatura inglesa",
        "Europeens",
        "Medicine in Literature",
        "Heart of darkness (Conrad, Joseph)",
        "Aufsatzsammlung",
        "Critique",
        "Roman anglais",
        "British and irish fiction (fictional works by one author)",
        "Africa, fiction",
        "Fiction, psychological",
        "Conrad, joseph, 1857-1924",
        "English fiction",
        "Voyages and travels",
        "Psychological aspects",
        "Sea stories",
        "Doppelgängers",
        "Fiction, general",
        "Discoveries in geography",
        "English language, textbooks for foreign speakers",
        "Dictionaries",
        "English language",
        "Spanish",
        "French",
        "In literature",
        "Imperialism in literature",
        "Korean",
        "Chinese",
        "German",
        "Européens",
        "Study guides",
        "Examinations",
        "Fiction, historical, general",
        "Psychological fiction",
        "Adaptations",
        "Comic books, strips",
        "COMICS & GRAPHIC NOVELS / Literary",
        "COMICS & GRAPHIC NOVELS / Adaptations",
        "Conrad, joseph, 1857-1924, juvenile literature",
        "Literary criticism",
        "European",
        "Good and evil",
        "Detective and mystery stories",
        "Imperialismo",
        "Europeos",
        "Degeneración",
        "Ficción",
        "Romans, nouvelles",
        "Sufrimiento",
        "Novela",
        "Inquisition",
        "Jews",
        "Persecutions",
        "History",
        "Comptoirs (Établissements de commerce)",
        "Dégénérescence",
        "Impérialisme",
        "Kolonialismus"
      ],
      "ia_collection": [
        "California-State-Suggested-Reading",
        "additional_collections",
        "americana",
        "binghamton-ol",
        "books",
        "claremont_school_of_theology",
        "cnusd-ol",
        "cua-ol",
        "delawarecountydistrictlibrary",
        "delawarecountydistrictlibrary-ol",
        "gwulibraries-ol",
        "inlibrary",
        "internetarchivebooks",
        "johnshopkins-ol",
        "phillipsacademy-preview",
        "printdisabled",
        "randolph-macon-college-ol",
        "riceuniversity-ol",
        "stmaryscountylibrary",
        "universityofcoloradoboulder-ol"
      ],
      "printdisabled": true,
      "lending_edition": "OL39477944M",
      "lending_identifier": "elcorazondelasti0000conr_p9o2",
      "authors": [
        {
          "key": "/authors/OL19441A",
          "name": "Joseph Conrad"
        }
      ],
      "first_publish_year": 1899,
      "ia": "elcorazondelasti0000conr_p9o2",
      "public_scan": true,
      "has_fulltext": true,
      "availability": {
        "status": "borrow_available",
        "available_to_browse": true,
        "available_to_borrow": true,
        "available_to_waitlist": false,
        "is_printdisabled": true,
        "is_readable": false,
        "is_lendable": true,
        "is_previewable": true,
        "identifier": "elcorazondelasti0000conr_p9o2",
        "isbn": "9789505155873",
        "oclc": null,
        "openlibrary_work": "OL28764583W",
        "openlibrary_edition": "OL39477944M",
        "last_loan_date": null,
        "num_waitlist": null,
        "last_waitlist_date": null,
        "is_restricted": true,
        "is_browseable": true,
        "__src__": "core.models.lending.get_availability"
      }
    },
    {
      "key": "/works/OL27064817W",
      "title": "Voyage Out",
      "edition_count": 465,
      "cover_id": 12621766,
      "cover_edition_key": null,
      "subject": [
        "Man-woman relationships, fiction",
        "Fiction, general",
        "Young women, fiction",
        "Young women -- Fiction",
        "Love stories",
        "Bildungsromans",
        "Ocean travel -- Fiction",
        "Women travelers -- Fiction",
        "British -- South America -- Fiction",
        "Fiction",
        "Ocean travel",
        "Young women",
        "Man-woman relationships",
        "Women travelers",
        "British",
        "Travel",
        "Social conditions",
        "Women",
        "Classic Literature",
        "British and irish fiction (fictional works by one author)",
        "South america, fiction",
        "Fiction, political",
        "Great britain, fiction",
        "Literature",
        "English literature",
        "Fiction, action & adventure",
        "Young women--travel",
        "Young women--travel--south america--fiction",
        "British--travel--south america--fiction",
        "Man-woman relationships--fiction",
        "Ocean travel--fiction",
        "Young women--fiction",
        "Women travelers--fiction",
        "Pr6045.o72 v68 1992",
        "823/.912",
        "British--south america--fiction",
        "Jeunes femmes",
        "Romans, nouvelles",
        "Relations entre hommes et femmes",
        "Voyageuses",
        "Long Now Manual for Civilization"
      ],
      "ia_collection": [
        "americana",
        "delawarecountydistrictlibrary",
        "inlibrary",
        "internetarchivebooks",
        "marygrovecollege",
        "printdisabled"
      ],
      "printdisabled": true,
      "lending_edition": "OL7640055M",
      "lending_identifier": "voyageout00woolgoog",
      "authors": [
        {
          "key": "/authors/OL19450A",
          "name": "Virginia Woolf"
        }
      ],
      "first_publish_year": 1915,
      "ia": "voyageout00woolgoog",
      "public_scan": true,
      "has_fulltext": true,
      "availability": {
        "status": "open",
        "available_to_browse": false,
        "available_to_borrow": false,
        "available_to_waitlist": false,
        "is_printdisabled": false,
        "is_readable": true,
        "is_lendable": false,
        "is_previewable": true,
        "identifier": "voyageout00woolgoog",
        "isbn": null,
        "oclc": null,
        "openlibrary_work": "OL14911879W",
        "openlibrary_edition": "OL7640055M",
        "last_loan_date": null,
        "num_waitlist": null,
        "last_waitlist_date": null,
        "is_restricted": false,
        "is_browseable": false,
        "__src__": "core.models.lending.get_availability"
      }
    },
    {
      "key": "/works/OL63996W",
      "title": "The Alhambra",
      "edition_count": 459,
      "cover_id": 8237030,
      "cover_edition_key": "OL13992397M",
      "subject": [
        "Alhambra",
        "Alhambra (Granada, España)",
        "Alhambra (Granada, Spain)",
        "Cuentos populares árabes",
        "Fiction",
        "Folklore",
        "History",
        "Inglés",
        "Islamic Architecture",
        "Juvenile literature",
        "Legends",
        "Libros de lectura",
        "Nonfiction",
        "Readers",
        "Social life and customs",
        "Tales",
        "Spanish language materials",
        "Travel",
        "Manners and customs",
        "Description and travel",
        "Cuentos norteamericanos",
        "Paleizen",
        "Alhambra (gebouw)",
        "Legenden",
        "Vida social y costumbres",
        "Ficción",
        "Leyendas",
        "Juvenile fiction",
        "Traducciones al español",
        "Cuentos",
        "Selecciones",
        "Literatura juvenil",
        "Irving, washington, 1783-1859",
        "Granada (spain), description and travel",
        "World history",
        "Personal memoirs",
        "American literature",
        "Palaces",
        "Fiction, general",
        "Spain, fiction",
        "Spain, description and travel"
      ],
      "ia_collection": [
        "YorkUniversity",
        "additional_collections",
        "americana",
        "barryuniversity-ol",
        "blc",
        "brigham_young_university",
        "cdl",
        "cua-ol",
        "denverpubliclibrary-ol",
        "inlibrary",
        "internetarchivebooks",
        "kellylibrary",
        "library_of_congress",
        "marygrovecollege",
        "microfilm",
        "openlibrary-d-ol",
        "printdisabled",
        "robarts",
        "schroederlibrary-ol",
        "toronto",
        "uconn_libraries",
        "university_of_alberta_libraries",
        "university_of_alberta_libraries_microfilm",
        "university_of_toronto",
        "universityofarizona-ol",
        "universityofoklahoma-ol"
      ],
      "printdisabled": true,
      "lending_edition": "OL51478616M",
      "lending_identifier": "alhambrabyirving0000wash_z7n6",
      "authors": [
        {
          "key": "/authors/OL19725A",
          "name": "Washington Irving"
        }
      ],
      "first_publish_year": 1800,
      "ia": "alhambrabyirving0000wash_z7n6",
      "public_scan": true,
      "has_fulltext": true,
      "availability": {
        "status": "open",
        "available_to_browse": false,
        "available_to_borrow": false,
        "available_to_waitlist": false,
        "is_printdisabled": false,
        "is_readable": true,
        "is_lendable": false,
        "is_previewable": true,
        "identifier": "alhambrabyirving0000wash_z7n6",
        "isbn": null,
        "oclc": null,
        "openlibrary_work": "OL63996W",
        "openlibrary_edition": "OL51478616M",
        "last_loan_date": null,
        "num_waitlist": null,
        "last_waitlist_date": null,
        "is_restricted": false,
        "is_browseable": false,
        "__src__": "core.models.lending.get_availability"
      }
    },
    {
      "key": "/works/OL1100007W",
      "title": "Le Tour du Monde en Quatre-Vingts Jours",
      "edition_count": 426,
      "cover_id": 6976035,
      "cover_edition_key": "OL7050533M",
      "subject": [
        "Viajes alrededor del mundo",
        "Translations into Gujarati",
        "Fiction",
        "Translations from French",
        "Children's stories, French",
        "Historical fiction",
        "Korean language materials",
        "Adventure and adventurers",
        "Open Library Staff Picks",
        "Children's stories, English",
        "Adventure stories",
        "Wagers",
        "French fiction",
        "Juvenile fiction",
        "Translations into English",
        "Voyages around the world",
        "Ficción",
        "Adventure fiction",
        "French Science fiction",
        "Submarines (Ships)",
        "Sea stories",
        "Science",
        "Continental european fiction (fictional works by one author)",
        "Fiction, action & adventure",
        "Children's fiction",
        "Voyages and travels, fiction",
        "Adventure and adventurers, fiction",
        "Balloons, fiction",
        "Large type books",
        "Travel",
        "Flights around the world",
        "English fiction",
        "Translations into French",
        "Readers",
        "French language",
        "Classic Literature",
        "British and irish fiction (fictional works by one author)",
        "Roman d'aventures",
        "Roman pour la jeunesse",
        "Spanish language books",
        "Spanish language",
        "English language",
        "Textbooks for foreign speakers",
        "Readers for new literates",
        "Travelers",
        "Criticism and interpretation",
        "Critique et interprétation",
        "Tour du monde en quatre-vingts jours (Verne, Jules)",
        "Aventures",
        "Romans",
        "Romans, nouvelles, etc. pour la jeunesse",
        "Littérature pour la jeunesse",
        "Ouvrages pour la jeunesse",
        "Voyages autour du monde",
        "Paris",
        "Employés de maison",
        "Policiers",
        "Erreur sur la personne",
        "Lectures et morceaux choisis",
        "Lecture (Enseignement Primaire)",
        "Problèmes et exercices",
        "Voyages",
        "Thriller",
        "Literatura",
        "Action & Adventure - General",
        "Weltreise",
        "Fantasy",
        "Romance literature",
        "Detectives, fiction",
        "March family (fictitious characters), fiction",
        "American fiction (fictional works by one author)",
        "Sisters, fiction",
        "Vols autour du monde",
        "Fiction, fantasy, general",
        "Illustraties",
        "Frans",
        "Comics & graphic novels, general",
        "Aeronautics",
        "Ke xue huan xiang xiao shuo",
        "Chang pian xiao shuo",
        "Romans, nouvelles",
        "General",
        "Suo xie ben",
        "Littérature française",
        "Histoire et critique",
        "Fiction, general",
        "Long Now Manual for Civilization",
        "Adventure",
        "Science fiction"
      ],
      "ia_collection": [
        "additional_collections",
        "americana",
        "belmont-ol",
        "booksbylanguage",
        "booksbylanguage_french",
        "bpljordan-ol",
        "cdl",
        "cnusd-ol",
        "cornell",
        "dartmouthlibrary-ol",
        "delawarecountydistrictlibrary",
        "delawarecountydistrictlibrary-ol",
        "europeanlibraries",
        "framingham-ol",
        "gwulibraries-ol",
        "hamiltonpubliclibrary-ol",
        "inlibrary",
        "internetarchivebooks",
        "kalamazoocollege-ol",
        "library_of_atlantis",
        "library_of_congress",
        "marygrovecollege",
        "newyorkpubliclibrary",
        "openlibrary-d-ol",
        "popularchinesebooks",
        "printdisabled",
        "robarts",
        "salisburyfreelibrary-ol",
        "sciencefiction",
        "toronto",
        "tulsacc-ol",
        "university_of_illinois_urbana-champaign",
        "university_of_toronto",
        "universityofoklahoma-ol",
        "universityofthewest-ol",
        "worthingtonlibraries-ol"
      ],
      "printdisabled": true,
      "lending_edition": "OL26195382M",
      "lending_identifier": "tourofworldineig00vern_1",
      "authors": [
        {
          "key": "/authors/OL113611A",
          "name": "Jules Verne"
        }
      ],
      "first_publish_year": 1872,
      "ia": "tourofworldineig00vern_1",
      "public_scan": true,
      "has_fulltext": true,
      "availability": {
        "status": "open",
        "available_to_browse": false,
        "available_to_borrow": false,
        "available_to_waitlist": false,
        "is_printdisabled": false,
        "is_readable": true,
        "is_lendable": false,
        "is_previewable": true,
        "identifier": "tourofworldineig00vern_1",
        "isbn": null,
        "oclc": null,
        "openlibrary_work": "OL17592151W",
        "openlibrary_edition": "OL26195382M",
        "last_loan_date": null,
        "num_waitlist": null,
        "last_waitlist_date": null,
        "is_restricted": false,
        "is_browseable": false,
        "__src__": "core.models.lending.get_availability"
      }
    },
    {
      "key": "/works/OL54059W",
      "title": "Roughing It",
      "edition_count": 408,
      "cover_id": 9165528,
      "cover_edition_key": "OL6970936M",
      "subject": [
        "19th century",
        "American Authors",
        "Biography",
        "Business",
        "Christian Science",
        "Description and travel",
        "Homes and haunts",
        "Intellectual life",
        "Journeys",
        "Law and politics",
        "Mines and mineral resources",
        "Travel",
        "Voyages around the world",
        "West (U.S.)",
        "Sexual ethics for teenagers",
        "Sex instruction for youth",
        "Sexual ethics",
        "Controversial literature",
        "Fiction",
        "West (u.s.), description and travel",
        "Twain, mark, 1835-1910",
        "American fiction (fictional works by one author)",
        "Law",
        "Hawaii, description and travel",
        "Voyages and travels",
        "American literature",
        "Fiction, action & adventure",
        "West (U.S.) -- Description and travel",
        "Twain, Mark, 1835-1910 -- Travel -- West (U.S.)",
        "Authors, American -- Homes and haunts -- West (U.S.)",
        "West (U.S.) -- Intellectual life -- 19th century",
        "Children's fiction",
        "Political aspects"
      ],
      "ia_collection": [
        "additional_collections",
        "americana",
        "americanuniversity-ol",
        "audio_bookspoetry",
        "barryuniversity-ol",
        "belmont-ol",
        "binghamton-ol",
        "brigham_young_university",
        "cdl",
        "cnusd-ol",
        "cornell",
        "cua-ol",
        "dartmouthlibrary-ol",
        "delawarecountydistrictlibrary",
        "delawarecountydistrictlibrary-ol",
        "denverpubliclibrary-ol",
        "drakeuniversity-ol",
        "framingham-ol",
        "gwulibraries-ol",
        "hamiltonpubliclibrary-ol",
        "inlibrary",
        "internetarchivebooks",
        "ithacacollege-ol",
        "johnshopkins-ol",
        "kalamazoocollege-ol",
        "library_of_atlantis",
        "library_of_congress",
        "librivoxaudio",
        "marymount-ol",
        "microfilm",
        "newberry",
        "occidentalcollegelibrary-ol",
        "openlibrary-d-ol",
        "printdisabled",
        "randolph-macon-college-ol",
        "riceuniversity-ol",
        "robarts",
        "rochester-ol",
        "spokanepubliclibrary-ol",
        "stmaryscountylibrary",
        "the-claremont-colleges-ol",
        "toronto",
        "trent_university",
        "tulsacc-ol",
        "unb-ol",
        "uni-ol",
        "university_of_alberta_libraries",
        "university_of_alberta_libraries_microfilm",
        "university_of_toronto",
        "universityofarizona-ol",
        "universityofcoloradoboulder-ol",
        "universityofoklahoma-ol",
        "utmississauga",
        "wilsoncollege-ol",
        "wrlc-ol"
      ],
      "printdisabled": true,
      "lending_edition": "OL31954465M",
      "lending_identifier": "completeworksofm06twai",
      "authors": [
        {
          "key": "/authors/OL18319A",
          "name": "Mark Twain"
        }
      ],
      "first_publish_year": 1872,
      "ia": "completeworksofm06twai",
      "public_scan": true,
      "has_fulltext": true,
      "availability": {
        "status": "open",
        "available_to_browse": false,
        "available_to_borrow": false,
        "available_to_waitlist": false,
        "is_printdisabled": false,
        "is_readable": true,
        "is_lendable": false,
        "is_previewable": true,
        "identifier": "completeworksofm06twai",
        "isbn": null,
        "oclc": null,
        "openlibrary_work": "OL54059W",
        "openlibrary_edition": "OL31954465M",
        "last_loan_date": null,
        "num_waitlist": null,
        "last_waitlist_date": null,
        "is_restricted": false,
        "is_browseable": false,
        "__src__": "core.models.lending.get_availability"
      }
    },
    {
      "key": "/works/OL848771W",
      "title": "Os Lusíadas",
      "edition_count": 367,
      "cover_id": 5943496,
      "cover_edition_key": "OL13523282M",
      "subject": [
        "Poetry",
        "History",
        "Discovery and exploration",
        "Description and travel",
        "Explorers",
        "Early works to 1800",
        "Portuguese Explorers",
        "Colonies",
        "Translations into English",
        "Spanish poetry",
        "Portuguese",
        "Epic poetry",
        "Concordances",
        "Portuguese Epic poetry",
        "Criticism and interpretation",
        "Facsimiles",
        "Manuscripts",
        "Portuguese poetry",
        "Translations from Portugese",
        "English poetry",
        "Travel",
        "Portuguese language",
        "Textbooks for foreign speakers",
        "English",
        "Gama, vasco da, 1469-1524",
        "Voyages and travels, poetry",
        "Continental european fiction (fictional works by one author)",
        "Portuguese language, study and teaching",
        "Romances",
        "Portuguese fiction",
        "Poetry (poetic works by one author)",
        "Portuguese literature",
        "Classical period",
        "Camoens",
        "Lusiads",
        "Poetry, history and criticism",
        "Language arts",
        "Spanish literature",
        "Asia",
        "Portuguese language reference",
        "Psychophysiology",
        "Foreign relations",
        "Catholic Church",
        "Translations from Portuguese"
      ],
      "ia_collection": [
        "JohnCarterBrownLibrary",
        "africanaspecialcollectionsduplessis",
        "africanlibraries",
        "americana",
        "belmont-ol",
        "binghamton-ol",
        "blc",
        "brigham_young_university",
        "cdl",
        "cornell",
        "cua-ol",
        "dartmouthlibrary-ol",
        "europeanlibraries",
        "globallibraries",
        "gwulibraries-ol",
        "inlibrary",
        "internetarchivebooks",
        "jcbfrench",
        "jcbportugalbrazil",
        "johnshopkins-ol",
        "library_of_congress",
        "marygrovecollege",
        "marymount-ol",
        "occidentalcollegelibrary-ol",
        "printdisabled",
        "riceuniversity-ol",
        "robarts",
        "rochester-ol",
        "the-claremont-colleges-ol",
        "thomasfisher",
        "toronto",
        "trent_university",
        "umassdartmouthclairetcarney",
        "unb-ol",
        "university_of_illinois_urbana-champaign",
        "university_of_toronto",
        "universityofarizona-ol",
        "universityofcoloradoboulder-ol",
        "universityofoklahoma-ol",
        "universityofottawa",
        "universityofpretorialibraryservices",
        "universityofthewest-ol"
      ],
      "printdisabled": true,
      "lending_edition": "OL33198114M",
      "lending_identifier": "oslusiadaspoemae00camo_0",
      "authors": [
        {
          "key": "/authors/OL73347A",
          "name": "Luís de Camões"
        },
        {
          "key": "/authors/OL12405770A",
          "name": "Souza Botelho"
        }
      ],
      "first_publish_year": 1572,
      "ia": "oslusiadaspoemae00camo_0",
      "public_scan": true,
      "has_fulltext": true,
      "availability": {
        "status": "open",
        "available_to_browse": false,
        "available_to_borrow": false,
        "available_to_waitlist": false,
        "is_printdisabled": false,
        "is_readable": true,
        "is_lendable": false,
        "is_previewable": true,
        "identifier": "oslusiadaspoemae00camo_0",
        "isbn": null,
        "oclc": null,
        "openlibrary_work": "OL848771W",
        "openlibrary_edition": "OL33198114M",
        "last_loan_date": null,
        "num_waitlist": null,
        "last_waitlist_date": null,
        "is_restricted": false,
        "is_browseable": false,
        "__src__": "core.models.lending.get_availability"
      }
    },
    {
      "key": "/works/OL1317211W",
      "title": "Meditations",
      "edition_count": 365,
      "cover_id": 211529,
      "cover_edition_key": "OL9863622M",
      "subject": [
        "Early works to 1800",
        "Philosophy",
        "Stoics",
        "Classic Literature",
        "Fiction",
        "Ethics",
        "Conduct of life",
        "Life",
        "Meditations",
        "Marcus aurelius, emperor of rome, 121-180",
        "Philosophy, ancient",
        "Conduct of life, early works to 1800",
        "Philosophy and ethics",
        "Boston (mass.), fiction",
        "Clergy, fiction",
        "Married people, fiction",
        "American fiction (fictional works by one author)",
        "Fiction, historical, general",
        "Fiction, psychological",
        "Wood-engraving, German",
        "Ethics & Moral Philosophy",
        "Emperors, rome",
        "Latin Authors",
        "Correspondence",
        "Emperors",
        "Orators",
        "B580 .g77 1983",
        "Authors, latin",
        "Authors, correspondence",
        "Self-help techniques",
        "Travel",
        "Contemporaries",
        "Description and travel",
        "Descriptions et voyages",
        "Ancient Philosophy",
        "Merchant mariners",
        "Missions and charities",
        "Charities",
        "New York. Mariners' family asylum, port of New York. [from old catalog]",
        "J©ơngere Stoa",
        "Stoa",
        "Ju ngere Stoa"
      ],
      "ia_collection": [
        "americana",
        "belmont-ol",
        "binghamton-ol",
        "blc",
        "brigham_young_university",
        "cdl",
        "claremont_school_of_theology",
        "cornell",
        "cua-ol",
        "dartmouthlibrary-ol",
        "delawarecountydistrictlibrary-ol",
        "denverpubliclibrary-ol",
        "drakeuniversity-ol",
        "europeanlibraries",
        "greatbooks",
        "greekclassicslist",
        "gwulibraries-ol",
        "harvardclassicssingles",
        "inlibrary",
        "internetarchivebooks",
        "kellylibrary",
        "library_of_congress",
        "marygrovecollege",
        "printdisabled",
        "riceuniversity-ol",
        "robarts",
        "rochester-ol",
        "toronto",
        "trent_university",
        "tulsacc-ol",
        "uconn_libraries",
        "uhmauicollege-ol",
        "unb-ol",
        "university_of_toronto",
        "universityofarizona-ol",
        "universityofcoloradoboulder-ol",
        "universityofoklahoma-ol",
        "worthingtonlibraries-ol"
      ],
      "printdisabled": true,
      "lending_edition": "OL7135383M",
      "lending_identifier": "marcusaureliusan00marcrich",
      "authors": [
        {
          "key": "/authors/OL133986A",
          "name": "Marcus Aurelius"
        }
      ],
      "first_publish_year": 1626,
      "ia": "marcusaureliusan00marcrich",
      "public_scan": true,
      "has_fulltext": true,
      "availability": {
        "status": "open",
        "available_to_browse": false,
        "available_to_borrow": false,
        "available_to_waitlist": false,
        "is_printdisabled": false,
        "is_readable": true,
        "is_lendable": false,
        "is_previewable": true,
        "identifier": "marcusaureliusan00marcrich",
        "isbn": null,
        "oclc": null,
        "openlibrary_work": "OL1317211W",
        "openlibrary_edition": "OL7135383M",
        "last_loan_date": null,
        "num_waitlist": null,
        "last_waitlist_date": null,
        "is_restricted": false,
        "is_browseable": false,
        "__src__": "core.models.lending.get_availability"
      }
    },
    {
      "key": "/works/OL63893W",
      "title": "The sketch-book of Geoffrey Crayon, Esq",
      "edition_count": 351,
      "cover_id": 7162030,
      "cover_edition_key": "OL6304982M",
      "subject": [
        "Fiction",
        "Description and travel",
        "Christmas",
        "Social life and customs",
        "Americans",
        "American Fantasy fiction",
        "Travel",
        "History",
        "American wit and humor",
        "Fiction, short stories (single author)",
        "American fiction (fictional works by one author)",
        "England, description and travel",
        "England, social life and customs",
        "Catskill mountains region (n.y.), fiction",
        "Classic Literature",
        "Literary Anthologies",
        "Short Stories",
        "Littérature américaine",
        "Text-books",
        "American literature",
        "Manuels",
        "Literary landmarks",
        "Christmas stories",
        "Voyages",
        "Américains",
        "Mœurs et coutumes",
        "Histoire",
        "Écrivains américains",
        "Romans",
        "Manners and customs",
        "Roman fantastique américain",
        "American Short stories",
        "American Authors",
        "Journeys"
      ],
      "ia_collection": [
        "YorkUniversity",
        "additional_collections",
        "americana",
        "binghamton-ol",
        "blc",
        "cdl",
        "cornell",
        "dartmouthlibrary-ol",
        "duke_libraries",
        "duljantz",
        "europeanlibraries",
        "inlibrary",
        "internetarchivebooks",
        "library_of_congress",
        "microfilm",
        "newyorkpubliclibrary",
        "printdisabled",
        "robarts",
        "toronto",
        "trent_university",
        "uconn_libraries",
        "university_of_alberta_libraries",
        "university_of_alberta_libraries_microfilm",
        "university_of_illinois_urbana-champaign",
        "university_of_toronto"
      ],
      "printdisabled": true,
      "lending_edition": "OL33212334M",
      "lending_identifier": "sketchbookofgeof00irvi_1",
      "authors": [
        {
          "key": "/authors/OL19725A",
          "name": "Washington Irving"
        }
      ],
      "first_publish_year": 1819,
      "ia": "sketchbookofgeof00irvi_1",
      "public_scan": true,
      "has_fulltext": true,
      "availability": {
        "status": "open",
        "available_to_browse": false,
        "available_to_borrow": false,
        "available_to_waitlist": false,
        "is_printdisabled": false,
        "is_readable": true,
        "is_lendable": false,
        "is_previewable": true,
        "identifier": "sketchbookofgeof00irvi_1",
        "isbn": null,
        "oclc": null,
        "openlibrary_work": "OL24984226W",
        "openlibrary_edition": "OL33212334M",
        "last_loan_date": null,
        "num_waitlist": null,
        "last_waitlist_date": null,
        "is_restricted": false,
        "is_browseable": false,
        "__src__": "core.models.lending.get_availability"
      }
    },
    {
      "key": "/works/OL38684W",
      "title": "Lord Jim",
      "edition_count": 344,
      "cover_id": 8236295,
      "cover_edition_key": "OL14020943M",
      "subject": [
        "Fiction",
        "British",
        "Officers",
        "Merchant marine",
        "Atonement",
        "Cowardice",
        "Fiction in English",
        "Travel",
        "Indonesia",
        "Seafaring life",
        "Conrad, Joseph, 1857-1924. Lord Jim",
        "English Psychological fiction",
        "English Adventure stories",
        "In literature",
        "Literature",
        "Classic Literature",
        "NOVELAS INGLESAS",
        "LITERARY CRITICISM / European / English, Irish, Scottish, Welsh",
        "Biography",
        "Criticism and interpretation",
        "Reading Level-Grade 11",
        "Reading Level-Grade 12",
        "British and irish fiction (fictional works by one author)",
        "Indonesia, fiction",
        "Fiction, psychological",
        "Children's fiction",
        "Sea stories",
        "Cultural policy",
        "Congresses",
        "Large type books",
        "New York Times reviewed",
        "Readers",
        "Adventure stories",
        "English Sea stories",
        "Sailors",
        "Europeans in Southeast Asia",
        "Self-fulfillment in men",
        "Fiction, sea stories",
        "High interest-low vocabulary books",
        "Readers for new literates",
        "Literatura",
        "Psychological fiction",
        "Dictionaries",
        "English language",
        "French",
        "German",
        "Korean",
        "Spanish",
        "Expiación",
        "Vida marinera",
        "Británicos",
        "Ficción psicológica",
        "Marina mercante",
        "Ficción",
        "Oficiales",
        "Atonement -- Fiction",
        "Merchant marine -- Officers -- Fiction",
        "British -- Indonesia -- Fiction",
        "Cowardice -- Fiction",
        "Indonesia -- Fiction",
        "Officiers de la marine marchande",
        "Romans, nouvelles",
        "Britanniques",
        "Lâcheté",
        "Livres en gros caractères",
        "Large print books",
        "LITERARY CRITICISM",
        "European",
        "English, Irish, Scottish, Welsh",
        "English language, textbooks for foreign speakers",
        "Long Now Manual for Civilization"
      ],
      "ia_collection": [
        "additional_collections",
        "americana",
        "americanuniversity-ol",
        "bannedbooks",
        "binghamton-ol",
        "cdl",
        "cornell",
        "cua-ol",
        "dartmouthlibrary-ol",
        "delawarecountydistrictlibrary",
        "delawarecountydistrictlibrary-ol",
        "drakeuniversity-ol",
        "framingham-ol",
        "gwulibraries-ol",
        "hamiltonpubliclibrary-ol",
        "inlibrary",
        "internetarchivebooks",
        "johnshopkins-ol",
        "library_of_atlantis",
        "library_of_congress",
        "marygrovecollege",
        "microfilm",
        "occidentalcollegelibrary-ol",
        "openlibrary-d-ol",
        "printdisabled",
        "riceuniversity-ol",
        "rochester-ol",
        "spokanepubliclibrary-ol",
        "stmaryscountylibrary",
        "the-claremont-colleges-ol",
        "toronto",
        "trent_university",
        "tulsacc-ol",
        "ualberta_historical_school",
        "ualbertawiedrick",
        "udc-ol",
        "unb-ol",
        "uni-ol",
        "university_of_alberta_libraries",
        "university_of_alberta_libraries_microfilm",
        "universityofarizona-ol",
        "universityofoklahoma-ol",
        "uslprototype",
        "wilsoncollege-ol",
        "worthingtonlibraries-ol"
      ],
      "printdisabled": true,
      "lending_edition": "OL26292312M",
      "lending_identifier": "lordjim00conr_3",
      "authors": [
        {
          "key": "/authors/OL19441A",
          "name": "Joseph Conrad"
        }
      ],
      "first_publish_year": 1900,
      "ia": "lordjim00conr_3",
      "public_scan": true,
      "has_fulltext": true,
      "availability": {
        "status": "open",
        "available_to_browse": null,
        "available_to_borrow": null,
        "available_to_waitlist": null,
        "is_printdisabled": null,
        "is_readable": null,
        "is_lendable": null,
        "is_previewable": true,
        "identifier": "lordjim00conr_3",
        "isbn": null,
        "oclc": null,
        "openlibrary_work": null,
        "openlibrary_edition": null,
        "last_loan_date": null,
        "num_waitlist": null,
        "last_waitlist_date": null,
        "is_restricted": false,
        "is_browseable": null,
        "__src__": "core.models.lending.get_availability"
      }
    },
    {
      "key": "/works/OL1815550W",
      "title": "Two years before the mast",
      "edition_count": 337,
      "cover_id": 8245243,
      "cover_edition_key": "OL6986131M",
      "subject": [
        "Alert (Brig : 1843-1862)",
        "Large-type books",
        "Pilgrim (Brig)",
        "Sailors",
        "Seafaring life",
        "Specimens",
        "Travel",
        "Viajes",
        "Vie en mer",
        "Voyages",
        "Voyages and travels",
        "Zamorano 80",
        "Dana, richard henry, 1815-1882",
        "Geography",
        "Biography",
        "Classic Literature",
        "Fiction",
        "Textual Criticism",
        "Parks & Campgrounds",
        "Museums, Tours, Points of Interest",
        "Hikes & Walks",
        "Budget",
        "SCIENCE",
        "Earth Sciences",
        "BIOGRAPHY & AUTOBIOGRAPHY",
        "General",
        "Two years before the mast (Dana, Richard Henry, Jr.)",
        "Seamen",
        "United states, history",
        "Fiction, action & adventure"
      ],
      "ia_collection": [
        "additional_collections",
        "americana",
        "binghamton-ol",
        "bostonpubliclibrary",
        "bplhoughton",
        "bpljordan-ol",
        "cdl",
        "cnusd-ol",
        "cornell",
        "dartmouthlibrary-ol",
        "delawarecountydistrictlibrary",
        "delawarecountydistrictlibrary-ol",
        "denverpubliclibrary-ol",
        "europeanlibraries",
        "fedlink",
        "framingham-ol",
        "greatbooks",
        "hamiltonpubliclibrary-ol",
        "harvardclassicssingles",
        "inlibrary",
        "internetarchivebooks",
        "library_of_atlantis",
        "library_of_congress",
        "marygrovecollege",
        "newyorkpubliclibrary",
        "printdisabled",
        "robarts",
        "spokanepubliclibrary-ol",
        "toronto",
        "trent_university",
        "unb-ol",
        "university_of_illinois_urbana-champaign",
        "university_of_toronto",
        "universityofcoloradoboulder-ol",
        "universityofoklahoma-ol",
        "zamorano80"
      ],
      "printdisabled": true,
      "lending_edition": "OL59087863M",
      "lending_identifier": "twoyearsbeforema00dana_6",
      "authors": [
        {
          "key": "/authors/OL217736A",
          "name": "Richard Henry Dana"
        }
      ],
      "first_publish_year": 1000,
      "ia": "twoyearsbeforema00dana_6",
      "public_scan": true,
      "has_fulltext": true,
      "availability": {
        "status": "open",
        "available_to_browse": false,
        "available_to_borrow": false,
        "available_to_waitlist": false,
        "is_printdisabled": false,
        "is_readable": true,
        "is_lendable": false,
        "is_previewable": true,
        "identifier": "twoyearsbeforema00dana_6",
        "isbn": null,
        "oclc": null,
        "openlibrary_work": "OL1815550W",
        "openlibrary_edition": "OL59087863M",
        "last_loan_date": null,
        "num_waitlist": null,
        "last_waitlist_date": null,
        "is_restricted": false,
        "is_browseable": false,
        "__src__": "core.models.lending.get_availability"
      }
    },
    {
      "key": "/works/OL413674W",
      "title": "Tom Sawyer Abroad",
      "edition_count": 333,
      "cover_id": 9162125,
      "cover_edition_key": "OL6970935M",
      "subject": [
        "Balloon ascensions",
        "Travel",
        "Tom Sawyer (Fictitious character)",
        "Americans",
        "Fiction",
        "Twain, mark, 1835-1910",
        "American fiction (fictional works by one author)",
        "Sawyer, tom (fictitious character), fiction",
        "Fiction, action & adventure",
        "Description and travel",
        "Political corruption",
        "Speculation",
        "Legislators",
        "Businessmen",
        "Intellectual life",
        "Homes and haunts",
        "American Authors",
        "Christian women saints",
        "History",
        "Imperialism",
        "Voyages around the world",
        "Impostors and imposture",
        "Boys",
        "Poor children",
        "Princes",
        "Walking",
        "Children's fiction",
        "Boys, fiction",
        "Adventure and adventurers, fiction",
        "Knights and knighthood",
        "Britons",
        "Kings and rulers",
        "Time travel",
        "Fiction, fantasy, general",
        "Fiction, coming of age",
        "Fiction, classics",
        "Juvenile Wit and humor",
        "Children",
        "Juvenile fiction",
        "Conduct of life",
        "Huckleberry Finn (Fictitious character)",
        "Jim (Fictitious character : Twain)",
        "Voyages and travels",
        "African Americans",
        "Friendship",
        "Adventure stories",
        "Inventors",
        "Kidnapping",
        "Desert animals",
        "Weddings",
        "Mississippi river, fiction",
        "Missouri, fiction",
        "Social life and customs",
        "American Humorous stories",
        "Storytelling",
        "City and town life",
        "American Detective and mystery stories",
        "Poor",
        "Mind and body",
        "Philosophy of mind",
        "Human beings",
        "Philosophical anthropology",
        "Arthurian romances",
        "Adaptations",
        "Christian Science",
        "Controversial literature",
        "Imaginary conversations",
        "Authorship",
        "Baconian theory",
        "Manners and customs",
        "Journeys"
      ],
      "ia_collection": [
        "additional_collections",
        "americana",
        "audio_bookspoetry",
        "belmont-ol",
        "bostonpubliclibrary",
        "bpljordan-ol",
        "bpljordanresearch",
        "cdl",
        "cnusd-ol",
        "delawarecountydistrictlibrary",
        "gutenberg",
        "inlibrary",
        "internetarchivebooks",
        "ithacacollege-ol",
        "johnshopkins-ol",
        "library_of_atlantis",
        "librivoxaudio",
        "marymount-ol",
        "microfilm",
        "printdisabled",
        "randolph-macon-college-ol",
        "rochester-ol",
        "toronto",
        "university_of_alberta_libraries",
        "university_of_alberta_libraries_microfilm",
        "universityofarizona-ol",
        "universityofcoloradoboulder-ol"
      ],
      "printdisabled": true,
      "lending_edition": "OL31959414M",
      "lending_identifier": "tomsawyerilmaili47411gut",
      "authors": [
        {
          "key": "/authors/OL18319A",
          "name": "Mark Twain"
        }
      ],
      "first_publish_year": 1894,
      "ia": "tomsawyerilmaili47411gut",
      "public_scan": true,
      "has_fulltext": true
    },
    {
      "key": "/works/OL63862W",
      "title": "Astoria",
      "edition_count": 321,
      "cover_id": 448955,
      "cover_edition_key": "OL2090015M",
      "subject": [
        "Overland journey to the Pacific coast",
        "Fur trade",
        "Descriptions et voyages",
        "Contributions in discoveries (in geography)",
        "Pacific Fur Co",
        "Description and travel. [from old catalog]",
        "Fourrures",
        "Description and travel",
        "Oregon",
        "Overland journeys to the Pacific. [from old catalog]",
        "Discovery and exploration",
        "Commerce",
        "Pacific Fur Company",
        "Overland journeys to the Pacific",
        "Indiens",
        "History",
        "Pacific fur company. [from old catalog]",
        "Indiens d'Amérique",
        "Indians of North America",
        "Voyages par terre jusqu'au Pacifique",
        "Sources",
        "American Fur Company",
        "Voyages to the Pacific coast",
        "Travel",
        "Astoria (or.)",
        "Northwestern states, description and travel",
        "Oregon, history",
        "Discoveries in geography",
        "American literature",
        "Fiction, westerns",
        "Fiction, historical, general",
        "Fiction, action & adventure",
        "Frontier and pioneer life, fiction",
        "Northwest, pacific, fiction"
      ],
      "ia_collection": [
        "additional_collections",
        "americana",
        "americanuniversity-ol",
        "barryuniversity-ol",
        "binghamton-ol",
        "brigham_young_university",
        "cdl",
        "cornell",
        "dartmouthlibrary-ol",
        "drakeuniversity-ol",
        "inlibrary",
        "internetarchivebooks",
        "ithacacollege-ol",
        "johnshopkins-ol",
        "library_of_congress",
        "marygrovecollege",
        "microfilm",
        "occidentalcollegelibrary-ol",
        "printdisabled",
        "robarts",
        "rochester-ol",
        "the-claremont-colleges-ol",
        "toronto",
        "trent_university",
        "unb-ol",
        "uni-ol",
        "university_of_alberta_libraries",
        "university_of_alberta_libraries_microfilm",
        "university_of_illinois_urbana-champaign",
        "university_of_toronto",
        "universityofarizona-ol",
        "universityofcoloradoboulder-ol",
        "universityofoklahoma-ol",
        "wilsoncollege-ol",
        "worksintranslation",
        "wrlc-ol"
      ],
      "printdisabled": true,
      "lending_edition": "OL46952430M",
      "lending_identifier": "astoriatheworkso0000wash",
      "authors": [
        {
          "key": "/authors/OL19725A",
          "name": "Washington Irving"
        }
      ],
      "first_publish_year": 1800,
      "ia": "astoriatheworkso0000wash",
      "public_scan": true,
      "has_fulltext": true,
      "availability": {
        "status": "open",
        "available_to_browse": false,
        "available_to_borrow": false,
        "available_to_waitlist": false,
        "is_printdisabled": false,
        "is_readable": true,
        "is_lendable": false,
        "is_previewable": true,
        "identifier": "astoriatheworkso0000wash",
        "isbn": null,
        "oclc": null,
        "openlibrary_work": "OL63862W",
        "openlibrary_edition": "OL46952430M",
        "last_loan_date": null,
        "num_waitlist": null,
        "last_waitlist_date": null,
        "is_restricted": false,
        "is_browseable": false,
        "__src__": "core.models.lending.get_availability"
      }
    },
    {
      "key": "/works/OL59979W",
      "title": "Sailing alone around the world",
      "edition_count": 296,
      "cover_id": 8247067,
      "cover_edition_key": "OL5851937M",
      "subject": [
        "Spray (Sloop)",
        "Single-handed sailing",
        "Sailing",
        "Yachting",
        "Travel",
        "Voyages and travels",
        "Voyages around the world",
        "Nonfiction",
        "Sailing, Single-handed",
        "Sailboats",
        "Liberdade (Ship)",
        "Biography & Autobiography",
        "History",
        "Slocum, joshua, 1844-1909",
        "Journeys",
        "Bateaux à voiles",
        "Voyages autour de monde",
        "Voyages autour du monde",
        "General",
        "Diaries",
        "Large type books",
        "Biography",
        "Nautical",
        "Slocum, Joshua, 1844- -- Travel",
        "Navigation à voile en solitaire"
      ],
      "ia_collection": [
        "additional_collections",
        "americana",
        "delawarecountydistrictlibrary",
        "inlibrary",
        "internetarchivebooks",
        "johnshopkins-ol",
        "library_of_atlantis",
        "library_of_congress",
        "microfilm",
        "openlibrary-d-ol",
        "printdisabled",
        "robarts",
        "stmaryscountylibrary",
        "toronto",
        "university_of_alberta_libraries",
        "university_of_alberta_libraries_microfilm",
        "university_of_toronto"
      ],
      "printdisabled": true,
      "lending_edition": "OL24592719M",
      "lending_identifier": "cihm_42110",
      "authors": [
        {
          "key": "/authors/OL31371A",
          "name": "Joshua Slocum"
        }
      ],
      "first_publish_year": 1800,
      "ia": "cihm_42110",
      "public_scan": true,
      "has_fulltext": true,
      "availability": {
        "status": "open",
        "available_to_browse": false,
        "available_to_borrow": false,
        "available_to_waitlist": false,
        "is_printdisabled": false,
        "is_readable": true,
        "is_lendable": false,
        "is_previewable": true,
        "identifier": "cihm_42110",
        "isbn": "0665421109",
        "oclc": null,
        "openlibrary_work": "OL15655875W",
        "openlibrary_edition": "OL24771345M",
        "last_loan_date": null,
        "num_waitlist": null,
        "last_waitlist_date": null,
        "is_restricted": false,
        "is_browseable": false,
        "__src__": "core.models.lending.get_availability"
      }
    },
    {
      "key": "/works/OL14869242W",
      "title": "Martin Chuzzlewit",
      "edition_count": 290,
      "cover_id": 13112817,
      "cover_edition_key": "OL44876296M",
      "subject": [
        "Social life and customs",
        "Literature",
        "Description and travel",
        "Travel",
        "British",
        "Fiction",
        "Avarice",
        "Grandfathers",
        "English",
        "Young men",
        "Classic Literature",
        "British and irish fiction (fictional works by one author)",
        "England, fiction",
        "United states, history, 19th century",
        "Great britain, history, 19th century",
        "Great britain, history, juvenile literature",
        "United states, history, juvenile literature",
        "Travelers",
        "Family relationships",
        "Caregivers",
        "Architects",
        "Hypocrisy",
        "Swindlers and swindling",
        "History",
        "English literature",
        "Fiction, humorous, general",
        "Fiction, classics",
        "Fiction, general",
        "Inheritance and succession",
        "United states, fiction",
        "Fiction, action & adventure",
        "Grandparents, fiction",
        "Children's fiction",
        "Long Now Manual for Civilization"
      ],
      "ia_collection": [
        "americana",
        "americanuniversity-ol",
        "audio_bookspoetry",
        "belmont-ol",
        "binghamton-ol",
        "cdl",
        "cornell",
        "delawarecountydistrictlibrary",
        "delawarecountydistrictlibrary-ol",
        "denverpubliclibrary-ol",
        "drakeuniversity-ol",
        "gutenberg",
        "gwulibraries-ol",
        "hamiltonpubliclibrary-ol",
        "inlibrary",
        "internetarchivebooks",
        "ithacacollege-ol",
        "kalamazoocollege-ol",
        "kellylibrary",
        "library_of_atlantis",
        "librivoxaudio",
        "marygrovecollege",
        "marymount-ol",
        "occidentalcollegelibrary-ol",
        "oliverwendellholmeslibrary",
        "openlibrary-d-ol",
        "phillipsacademy",
        "printdisabled",
        "randolph-macon-college-ol",
        "riceuniversity-ol",
        "robarts",
        "rochester-ol",
        "the-claremont-colleges-ol",
        "toronto",
        "trent_university",
        "unb-ol",
        "university_of_toronto",
        "universityofarizona-ol",
        "universityofcoloradoboulder-ol",
        "universityofoklahoma-ol",
        "wilsoncollege-ol",
        "wrlc-ol"
      ],
      "printdisabled": true,
      "lending_edition": "OL47307703M",
      "lending_identifier": "worksofcharlesdi0000char",
      "authors": [
        {
          "key": "/authors/OL24638A",
          "name": "Charles Dickens"
        }
      ],
      "first_publish_year": 1800,
      "ia": "worksofcharlesdi0000char",
      "public_scan": true,
      "has_fulltext": true,
      "availability": {
        "status": "open",
        "available_to_browse": false,
        "available_to_borrow": false,
        "available_to_waitlist": false,
        "is_printdisabled": false,
        "is_readable": true,
        "is_lendable": false,
        "is_previewable": true,
        "identifier": "worksofcharlesdi0000char",
        "isbn": null,
        "oclc": null,
        "openlibrary_work": "OL14869242W",
        "openlibrary_edition": "OL47307703M",
        "last_loan_date": null,
        "num_waitlist": null,
        "last_waitlist_date": null,
        "is_restricted": false,
        "is_browseable": false,
        "__src__": "core.models.lending.get_availability"
      }
    },
    {
      "key": "/works/OL471576W",
      "title": "Murder on the Orient Express",
      "edition_count": 247,
      "cover_id": 11100465,
      "cover_edition_key": "OL32440766M",
      "subject": [
        "Agatha Christie",
        "Private investigator",
        "P.I.",
        "Hercule Poirot",
        "Detective",
        "Murder",
        "Mystery",
        "Juvenile",
        "Humour",
        "Fiction",
        "Literature",
        "Stories",
        "Private investigators",
        "Private investigators in fiction",
        "Travel",
        "Railroad",
        "Trains",
        "Express trains",
        "Orient Express",
        "Littérature anglaise",
        "Roman anglais",
        "Orient Express (Express train)",
        "Regény",
        "Angol irodalom",
        "Hercule Poirot (Fictitious character)",
        "Detective and mystery stories",
        "Railroad stories",
        "Railroad travel",
        "Poirot, Hercule (Personaje literario)",
        "Novela policíaca",
        "Ficción",
        "Investigation",
        "Juvenile fiction",
        "Poirot, hercule (fictitious character), fiction",
        "Private investigators, fiction",
        "Fiction, mystery & detective, traditional",
        "French imprints",
        "Translations into French",
        "English Detective and mystery stories",
        "French fiction",
        "English fiction",
        "English literature",
        "Readers",
        "English language, textbooks for foreign speakers",
        "Hercule Poirot (Fictional character)",
        "Mystery fiction",
        "Large type books",
        "Dorian. Grey (Fictitious character)",
        "Détectives",
        "Romans, nouvelles",
        "Orient-Express (Train rapide)",
        "Meurtre",
        "Enquêtes",
        "Spanish language materials",
        "Novela",
        "Detectives privados",
        "Comics & graphic novels, crime & mystery",
        "American literature"
      ],
      "ia_collection": [
        "americana",
        "cnusd-ol",
        "dartmouthlibrary-ol",
        "delawarecountydistrictlibrary",
        "delawarecountydistrictlibrary-ol",
        "goffstownlibrary-ol",
        "inlibrary",
        "internetarchivebooks",
        "johnshopkins-ol",
        "library_of_atlantis",
        "marymount-ol",
        "miltonpubliclibrary-ol",
        "occidentalcollegelibrary-ol",
        "openlibrary-d-ol",
        "printdisabled",
        "rochester-ol",
        "spokanepubliclibrary-ol",
        "stmaryscountylibrary",
        "tulsacc-ol",
        "universityofarizona-ol",
        "universityofcoloradoboulder-ol",
        "worthingtonlibraries-ol"
      ],
      "printdisabled": true,
      "lending_edition": "OL47706405M",
      "lending_identifier": "lecrimedelorient0000agat_p1p4",
      "authors": [
        {
          "key": "/authors/OL27695A",
          "name": "Agatha Christie"
        }
      ],
      "first_publish_year": 1933,
      "ia": "lecrimedelorient0000agat_p1p4",
      "public_scan": false,
      "has_fulltext": true,
      "availability": {
        "status": "borrow_available",
        "available_to_browse": true,
        "available_to_borrow": false,
        "available_to_waitlist": false,
        "is_printdisabled": true,
        "is_readable": false,
        "is_lendable": true,
        "is_previewable": true,
        "identifier": "lecrimedelorient0000agat_p1p4",
        "isbn": "9782702436332",
        "oclc": null,
        "openlibrary_work": "OL471576W",
        "openlibrary_edition": "OL47706405M",
        "last_loan_date": null,
        "num_waitlist": null,
        "last_waitlist_date": null,
        "is_restricted": true,
        "is_browseable": true,
        "__src__": "core.models.lending.get_availability"
      }
    },
    {
      "key": "/works/OL276328W",
      "title": "Daisy Miller",
      "edition_count": 244,
      "cover_id": 6482238,
      "cover_edition_key": "OL22327453M",
      "subject": [
        "Fiction",
        "Americans",
        "Young women",
        "Americans in fiction",
        "Young women in fiction",
        "Europe in fiction",
        "Drama",
        "Social life and customs",
        "United States in fiction",
        "Women travelers",
        "Motion picture plays",
        "Travel",
        "Classic Literature",
        "Historical Fiction",
        "Romance",
        "Juvenile fiction",
        "History",
        "Adventure and adventurers",
        "Ghost stories",
        "Horror tales",
        "American National characteristics",
        "Animals",
        "Children's stories, English",
        "Short stories",
        "Jungles",
        "Mowgli (Fictitious character)",
        "American fiction (fictional works by one author)",
        "Europe, fiction",
        "Young women, fiction",
        "Fiction, psychological",
        "Large type books",
        "Horses",
        "Vampires",
        "American literature",
        "Americans--europe--fiction",
        "Ps2116 .d3 2007",
        "813.4"
      ],
      "ia_collection": [
        "California-State-Suggested-Reading",
        "additional_collections",
        "americana",
        "blc",
        "books",
        "cdl",
        "delawarecountydistrictlibrary",
        "inlibrary",
        "internetarchivebooks",
        "library_of_congress",
        "printdisabled",
        "uconn_libraries",
        "university_of_illinois_urbana-champaign"
      ],
      "printdisabled": true,
      "lending_edition": "OL7196288M",
      "lending_identifier": "daisymillerintep00jamerich",
      "authors": [
        {
          "key": "/authors/OL21001A",
          "name": "Henry James"
        }
      ],
      "first_publish_year": 1877,
      "ia": "daisymillerintep00jamerich",
      "public_scan": true,
      "has_fulltext": true,
      "availability": {
        "status": "open",
        "available_to_browse": false,
        "available_to_borrow": false,
        "available_to_waitlist": false,
        "is_printdisabled": false,
        "is_readable": true,
        "is_lendable": false,
        "is_previewable": true,
        "identifier": "daisymillerintep00jamerich",
        "isbn": null,
        "oclc": null,
        "openlibrary_work": "OL276328W",
        "openlibrary_edition": "OL7196288M",
        "last_loan_date": null,
        "num_waitlist": null,
        "last_waitlist_date": null,
        "is_restricted": false,
        "is_browseable": false,
        "__src__": "core.models.lending.get_availability"
      }
    },
    {
      "key": "/works/OL145191W",
      "title": "Picasso",
      "edition_count": 240,
      "cover_id": 2238306,
      "cover_edition_key": "OL9101853M",
      "subject": [
        "20th century",
        "Amsterdam (Netherlands)",
        "Amsterdam (Netherlands). Stedelijk Museum",
        "Animals",
        "Animals in art",
        "Anniversaries",
        "Art",
        "Art collections",
        "Avant-garde (Aesthetics)",
        "Ballet",
        "Bullfighters in art",
        "Bullfights in art",
        "Bulls in art",
        "Catalogs",
        "Ceramic sculpture",
        "Ceramics",
        "Contributions in theater",
        "Costume",
        "Crawford Municipal Art Gallery",
        "Criticism and interpretation",
        "Cubism",
        "Drawing",
        "Etching",
        "Exhibitions",
        "Expositions",
        "France",
        "French Pottery",
        "Galerie Beyeler",
        "Germany",
        "Graphic arts",
        "Hamburger Kunsthalle",
        "History",
        "Human beings in art",
        "Influence",
        "Italy",
        "Jan Krugier Gallery (New York, N.Y.)",
        "Journeys",
        "Kunstmuseum Heidenheim",
        "Linoleum block printing",
        "Linoleum block-printing",
        "Lithography",
        "Minotaur (Greek mythology)",
        "Modern Art",
        "Modernism (Art)",
        "Museo Picasso",
        "Museum Ludwig",
        "Museum of Modern Art (New York, N.Y.)",
        "Musée Picasso (Paris, France)",
        "Musée Réattu",
        "National Gallery of Australia",
        "Painting",
        "Philosophy",
        "Pictorial works",
        "Portraits",
        "Posters",
        "Pottery",
        "Primitivism in art",
        "Prints",
        "Private collections",
        "Richard Harris Collection",
        "Spain",
        "Spanish Drawing",
        "Spanish Posters",
        "Spanish Prints",
        "Spanish Watercolor painting",
        "Staatliche Kunstsammlungen Dresden",
        "Staatliche Kunstsammlungen Dresden. Kupferstich-Kabinett",
        "Stage-setting and scenery",
        "Tacoma Art Museum",
        "Travel",
        "Women in art",
        "Appropriation (Art)",
        "Biography",
        "Artists",
        "Exhibition catalogues and specific collections",
        "Individual artists",
        "Individual Painters - 20th Century",
        "Museology (General)",
        "Art & Art Instruction",
        "Individual Artist",
        "Art / Individual Artist",
        "Landscapes in art",
        "Outdoor sculpture",
        "Artists' preparatory studies",
        "Last years",
        "Imitation in art",
        "Erotic drawing",
        "Picasso, pablo, 1881-1973",
        "French Art",
        "Painting, spanish",
        "Catalogues d'exposition",
        "Cubismo",
        "Museu Nacional d'Art de Catalunya",
        "Linoleumsneden",
        "Painting, exhibitions",
        "Mithras (Zoroastrian deity)",
        "Erotic art",
        "Art, modern, 20th century, exhibitions",
        "Spanish Pottery",
        "Museum Würth",
        "Falla, manuel de, 1876-1946",
        "Clothing",
        "Notebooks, sketchbooks",
        "Painters",
        "Catalogues raisonnés"
      ],
      "ia_collection": [
        "inlibrary",
        "internetarchivebooks",
        "printdisabled"
      ],
      "printdisabled": true,
      "lending_edition": "OL19865248M",
      "lending_identifier": "lhommeaumoutonpi0000pica",
      "authors": [
        {
          "key": "/authors/OL44790A",
          "name": "Pablo Picasso"
        },
        {
          "key": "/authors/OL3225101A",
          "name": "Jean-Louis Andral"
        },
        {
          "key": "/authors/OL139551A",
          "name": "Pierre Daix"
        }
      ],
      "first_publish_year": 1926,
      "ia": "lhommeaumoutonpi0000pica",
      "public_scan": false,
      "has_fulltext": true,
      "availability": {
        "status": "borrow_available",
        "available_to_browse": true,
        "available_to_borrow": false,
        "available_to_waitlist": false,
        "is_printdisabled": true,
        "is_readable": false,
        "is_lendable": true,
        "is_previewable": true,
        "identifier": "lhommeaumoutonpi0000pica",
        "isbn": "2711838250",
        "oclc": null,
        "openlibrary_work": "OL145191W",
        "openlibrary_edition": "OL19865248M",
        "last_loan_date": null,
        "num_waitlist": null,
        "last_waitlist_date": null,
        "is_restricted": true,
        "is_browseable": true,
        "__src__": "core.models.lending.get_availability"
      }
    },
    {
      "key": "/works/OL16234621W",
      "title": "Life of Samuel Johnson",
      "edition_count": 238,
      "cover_id": 5785491,
      "cover_edition_key": "OL14020324M",
      "subject": [
        "Biography",
        "Description and travel",
        "English Authors",
        "Early works to 1800",
        "Interviews",
        "Lexicographers",
        "KDescr. & trav",
        "Intellectual life",
        "Critics",
        "Intellectuals",
        "Johnson, Samuel, 1709-1784",
        "Authors, English",
        "SAMUEL JOHNSON",
        "Authors, biography",
        "Biografie",
        "Travel",
        "British and irish fiction (fictional works by one author)",
        "Long Now Manual for Civilization",
        "Miscelanea Inglesa (Literatura)",
        "Obras Gerais"
      ],
      "ia_collection": [
        "americana",
        "brighamyounguniversityidaho",
        "cdl",
        "dartmouthlibrary-ol",
        "duke_libraries",
        "europeanlibraries",
        "family_history_library",
        "hamiltonpubliclibrary-ol",
        "inlibrary",
        "internetarchivebooks",
        "kellylibrary",
        "newyorkpubliclibrary",
        "printdisabled",
        "robarts",
        "toronto",
        "trent_university",
        "university_of_toronto"
      ],
      "printdisabled": true,
      "lending_edition": "OL7137439M",
      "lending_identifier": "boswellslifeofjo00boswiala",
      "authors": [
        {
          "key": "/authors/OL348127A",
          "name": "James Boswell"
        }
      ],
      "first_publish_year": 1776,
      "ia": "boswellslifeofjo00boswiala",
      "public_scan": true,
      "has_fulltext": true,
      "availability": {
        "status": "open",
        "available_to_browse": false,
        "available_to_borrow": false,
        "available_to_waitlist": false,
        "is_printdisabled": false,
        "is_readable": true,
        "is_lendable": false,
        "is_previewable": true,
        "identifier": "boswellslifeofjo00boswiala",
        "isbn": null,
        "oclc": null,
        "openlibrary_work": "OL16234621W",
        "openlibrary_edition": "OL7137439M",
        "last_loan_date": null,
        "num_waitlist": null,
        "last_waitlist_date": null,
        "is_restricted": false,
        "is_browseable": false,
        "__src__": "core.models.lending.get_availability"
      }
    }
  ]
}
