{
  "book": {
    "id": 205987,
    "title": "Poor Things",
    "contributions": [
      {
        "author": {
          "name": "Alasdair Gray"
        }
      }
    ],
    "description": "Godwin Baxter's scientific ambition to create the perfect companion is realized when he finds the drowned body of the beautiful Bella, who he brings back to life in a Frankenstein-esque feat. But his dream is thwarted by Dr. Archibald McCandless's jealous love for his creation...\n\nBut what does Bella think?\n\nThis story of true love and scientific daring whirls the listeners from the private operating-theatres of late-Victorian Glasgow through aristocratic casinos, low-life Alexandria and a Parisian bordello, reaching an interrupted climax in a Scottish church.",
    "images": [
      {
        "url": "https://assets.hardcover.app/books/205987/115122-L.jpg"
      }
    ],
    "taggings": [
      {
        "tag": {
          "tag": "Classics"
        }
      },
      {
        "tag": {
          "tag": "Fantasy"
        }
      },
      {
        "tag": {
          "tag": "Fiction"
        }
      },
      {
        "tag": {
          "tag": "Science fiction"
        }
      },
      {
        "tag": {
          "tag": "dark"
        }
      },
      {
        "tag": {
          "tag": "adventure"
        }
      },
      {
        "tag": {
          "tag": "funny"
        }
      },
      {
        "tag": {
          "tag": "moderate pacing"
        }
      },
      {
        "tag": {
          "tag": "Strong Character Development"
        }
      },
      {
        "tag": {
          "tag": "Loveable Characters"
        }
      }
    ]
  }
}
